[{"state_code":"01","statename":"JAMMU AND KASHMIR","total_txn_sold_to_other_state":"1167","total_txn_lifted_by_other_state":"83","total_qty_sold_to_other_state":"22916.0","total_qty_lifted_by_other_state":"1570.0","month":"4","year":"123"},{"state_code":"02","statename":"HIMACHAL PRADESH","total_txn_sold_to_other_state":"5749","total_txn_lifted_by_other_state":"54","total_qty_sold_to_other_state":"137517.4","total_qty_lifted_by_other_state":"1120.8","month":"4","year":"123"},{"state_code":"03","statename":"PUNJAB","total_txn_sold_to_other_state":"18","total_txn_lifted_by_other_state":"0","total_qty_sold_to_other_state":"385","total_qty_lifted_by_other_state":"0","month":"4","year":"123"},{"state_code":"04","statename":"CHANDIGARH","total_txn_sold_to_other_state":"13","total_txn_lifted_by_other_state":"0","total_qty_sold_to_other_state":"200","total_qty_lifted_by_other_state":"0","month":"4","year":"123"},{"state_code":"05","statename":"UTTARAKHAND","total_txn_sold_to_other_state":"4962","total_txn_lifted_by_other_state":"2696","total_qty_sold_to_other_state":"118843.0","total_qty_lifted_by_other_state":"34325.96","month":"4","year":"123"},{"state_code":"06","statename":"HARYANA","total_txn_sold_to_other_state":"35024","total_txn_lifted_by_other_state":"91","total_qty_sold_to_other_state":"845276.138","total_qty_lifted_by_other_state":"94","month":"4","year":"123"},{"state_code":"07","statename":"DELHI","total_txn_sold_to_other_state":"217416","total_txn_lifted_by_other_state":"1873","total_qty_sold_to_other_state":"4605750.60","total_qty_lifted_by_other_state":"25372.08","month":"4","year":"123"},{"state_code":"08","statename":"RAJASTHAN","total_txn_sold_to_other_state":"8171","total_txn_lifted_by_other_state":"2390","total_qty_sold_to_other_state":"207070.01","total_qty_lifted_by_other_state":"50929.2","month":"4","year":"123"},{"state_code":"09","statename":"UTTAR PRADESH","total_txn_sold_to_other_state":"0","total_txn_lifted_by_other_state":"123181","total_qty_sold_to_other_state":"0","total_qty_lifted_by_other_state":"2528783.00","month":"4","year":"123"},{"state_code":"10","statename":"BIHAR","total_txn_sold_to_other_state":"3209","total_txn_lifted_by_other_state":"155878","total_qty_sold_to_other_state":"38571.68","total_qty_lifted_by_other_state":"3557634.726","month":"4","year":"123"},{"state_code":"11","statename":"SIKKIM","total_txn_sold_to_other_state":"59","total_txn_lifted_by_other_state":"0","total_qty_sold_to_other_state":"1250","total_qty_lifted_by_other_state":"0","month":"4","year":"123"},{"state_code":"16","statename":"TRIPURA","total_txn_sold_to_other_state":"0","total_txn_lifted_by_other_state":"10","total_qty_sold_to_other_state":"0","total_qty_lifted_by_other_state":"199.5","month":"4","year":"123"},{"state_code":"17","statename":"MEGHALAYA","total_txn_sold_to_other_state":"13","total_txn_lifted_by_other_state":"0","total_qty_sold_to_other_state":"270","total_qty_lifted_by_other_state":"0","month":"4","year":"123"},{"state_code":"18","statename":"ASSAM","total_txn_sold_to_other_state":"0","total_txn_lifted_by_other_state":"179","total_qty_sold_to_other_state":"0","total_qty_lifted_by_other_state":"2721.0","month":"4","year":"123"},{"state_code":"19","statename":"WEST BENGAL","total_txn_sold_to_other_state":"701","total_txn_lifted_by_other_state":"1269","total_qty_sold_to_other_state":"15114.7","total_qty_lifted_by_other_state":"24020.51","month":"4","year":"123"},{"state_code":"20","statename":"JHARKHAND","total_txn_sold_to_other_state":"822","total_txn_lifted_by_other_state":"4151","total_qty_sold_to_other_state":"18592.75","total_qty_lifted_by_other_state":"83492.61","month":"4","year":"123"},{"state_code":"21","statename":"ORISSA","total_txn_sold_to_other_state":"1","total_txn_lifted_by_other_state":"158","total_qty_sold_to_other_state":"9","total_qty_lifted_by_other_state":"3215","month":"4","year":"123"},{"state_code":"22","statename":"CHHATISGARH","total_txn_sold_to_other_state":"103","total_txn_lifted_by_other_state":"802","total_qty_sold_to_other_state":"1890","total_qty_lifted_by_other_state":"14532.00","month":"4","year":"123"},{"state_code":"23","statename":"MADHYA PRADESH","total_txn_sold_to_other_state":"1781","total_txn_lifted_by_other_state":"14733","total_qty_sold_to_other_state":"22225.2","total_qty_lifted_by_other_state":"342199.2","month":"4","year":"123"},{"state_code":"24","statename":"GUJARAT","total_txn_sold_to_other_state":"6531","total_txn_lifted_by_other_state":"539","total_qty_sold_to_other_state":"148675.25","total_qty_lifted_by_other_state":"13918.1","month":"4","year":"123"},{"state_code":"25","statename":"DAMAN & DIU","total_txn_sold_to_other_state":"3936","total_txn_lifted_by_other_state":"7","total_qty_sold_to_other_state":"93701.72","total_qty_lifted_by_other_state":"155","month":"4","year":"123"},{"state_code":"27","statename":"MAHARASHTRA","total_txn_sold_to_other_state":"19990","total_txn_lifted_by_other_state":"1767","total_qty_sold_to_other_state":"413393.209","total_qty_lifted_by_other_state":"35939.47","month":"4","year":"123"},{"state_code":"28","statename":"ANDHRA PRADESH","total_txn_sold_to_other_state":"0","total_txn_lifted_by_other_state":"565","total_qty_sold_to_other_state":"0","total_qty_lifted_by_other_state":"10640","month":"4","year":"123"},{"state_code":"29","statename":"KARNATAKA","total_txn_sold_to_other_state":"548","total_txn_lifted_by_other_state":"837","total_qty_sold_to_other_state":"11131","total_qty_lifted_by_other_state":"15524.60","month":"4","year":"123"},{"state_code":"30","statename":"GOA","total_txn_sold_to_other_state":"548","total_txn_lifted_by_other_state":"7","total_qty_sold_to_other_state":"11784.5","total_qty_lifted_by_other_state":"115","month":"4","year":"123"},{"state_code":"32","statename":"KERALA","total_txn_sold_to_other_state":"777","total_txn_lifted_by_other_state":"67","total_qty_sold_to_other_state":"11628","total_qty_lifted_by_other_state":"943.5","month":"4","year":"123"},{"state_code":"33","statename":"TAMIL NADU","total_txn_sold_to_other_state":"406","total_txn_lifted_by_other_state":"2207","total_qty_sold_to_other_state":"4154.12","total_qty_lifted_by_other_state":"12750.021","month":"4","year":"123"},{"state_code":"34","statename":"PUDUCHERRY","total_txn_sold_to_other_state":"194","total_txn_lifted_by_other_state":"0","total_qty_sold_to_other_state":"970","total_qty_lifted_by_other_state":"0","month":"4","year":"123"},{"state_code":"35","statename":"ANDAMAN & NICOBAR ISLANDS","total_txn_sold_to_other_state":"10","total_txn_lifted_by_other_state":"0","total_qty_sold_to_other_state":"160.0","total_qty_lifted_by_other_state":"0","month":"4","year":"123"},{"state_code":"36","statename":"TELANGANA","total_txn_sold_to_other_state":"1391","total_txn_lifted_by_other_state":"0","total_qty_sold_to_other_state":"28699","total_qty_lifted_by_other_state":"0","month":"4","year":"123"},{"state_code":"37","statename":"LADAKH","total_txn_sold_to_other_state":"4","total_txn_lifted_by_other_state":"0","total_qty_sold_to_other_state":"17","total_qty_lifted_by_other_state":"0","month":"4","year":"123"}]
