[{"state_code":"01","statename":"JAMMU AND KASHMIR","total_txn_sold_to_other_state":"891","total_txn_lifted_by_other_state":"42","total_qty_sold_to_other_state":"10490.611","total_qty_lifted_by_other_state":"1437.00","month":"6","year":"122"},{"state_code":"02","statename":"HIMACHAL PRADESH","total_txn_sold_to_other_state":"953","total_txn_lifted_by_other_state":"61","total_qty_sold_to_other_state":"42556.85","total_qty_lifted_by_other_state":"2503.528","month":"6","year":"122"},{"state_code":"03","statename":"PUNJAB","total_txn_sold_to_other_state":"158","total_txn_lifted_by_other_state":"52","total_qty_sold_to_other_state":"5197","total_qty_lifted_by_other_state":"912.0","month":"6","year":"122"},{"state_code":"04","statename":"CHANDIGARH","total_txn_sold_to_other_state":"4","total_txn_lifted_by_other_state":"0","total_qty_sold_to_other_state":"55","total_qty_lifted_by_other_state":"0","month":"6","year":"122"},{"state_code":"05","statename":"UTTARAKHAND","total_txn_sold_to_other_state":"482","total_txn_lifted_by_other_state":"2015","total_qty_sold_to_other_state":"12410.0","total_qty_lifted_by_other_state":"54839.532","month":"6","year":"122"},{"state_code":"06","statename":"HARYANA","total_txn_sold_to_other_state":"10136","total_txn_lifted_by_other_state":"2647","total_qty_sold_to_other_state":"474428.467","total_qty_lifted_by_other_state":"108071.815","month":"6","year":"122"},{"state_code":"07","statename":"DELHI","total_txn_sold_to_other_state":"90320","total_txn_lifted_by_other_state":"683","total_qty_sold_to_other_state":"4033118.421","total_qty_lifted_by_other_state":"24766.998","month":"6","year":"122"},{"state_code":"08","statename":"RAJASTHAN","total_txn_sold_to_other_state":"1157","total_txn_lifted_by_other_state":"2402","total_qty_sold_to_other_state":"54998.51","total_qty_lifted_by_other_state":"98428.206","month":"6","year":"122"},{"state_code":"10","statename":"BIHAR","total_txn_sold_to_other_state":"1105","total_txn_lifted_by_other_state":"93196","total_qty_sold_to_other_state":"44472","total_qty_lifted_by_other_state":"4195740.323","month":"6","year":"122"},{"state_code":"11","statename":"SIKKIM","total_txn_sold_to_other_state":"41","total_txn_lifted_by_other_state":"0","total_qty_sold_to_other_state":"1420","total_qty_lifted_by_other_state":"0","month":"6","year":"122"},{"state_code":"12","statename":"ARUNACHAL PRADESH","total_txn_sold_to_other_state":"15","total_txn_lifted_by_other_state":"0","total_qty_sold_to_other_state":"670","total_qty_lifted_by_other_state":"0","month":"6","year":"122"},{"state_code":"13","statename":"NAGALAND","total_txn_sold_to_other_state":"10","total_txn_lifted_by_other_state":"7","total_qty_sold_to_other_state":"270","total_qty_lifted_by_other_state":"284.00","month":"6","year":"122"},{"state_code":"16","statename":"TRIPURA","total_txn_sold_to_other_state":"26","total_txn_lifted_by_other_state":"13","total_qty_sold_to_other_state":"1035","total_qty_lifted_by_other_state":"516.00","month":"6","year":"122"},{"state_code":"17","statename":"MEGHALAYA","total_txn_sold_to_other_state":"2","total_txn_lifted_by_other_state":"0","total_qty_sold_to_other_state":"55","total_qty_lifted_by_other_state":"0","month":"6","year":"122"},{"state_code":"18","statename":"ASSAM","total_txn_sold_to_other_state":"3","total_txn_lifted_by_other_state":"20","total_qty_sold_to_other_state":"76","total_qty_lifted_by_other_state":"25.969","month":"6","year":"122"},{"state_code":"19","statename":"WEST BENGAL","total_txn_sold_to_other_state":"11","total_txn_lifted_by_other_state":"942","total_qty_sold_to_other_state":"560","total_qty_lifted_by_other_state":"36987.088","month":"6","year":"122"},{"state_code":"20","statename":"JHARKHAND","total_txn_sold_to_other_state":"268","total_txn_lifted_by_other_state":"2471","total_qty_sold_to_other_state":"11394.02","total_qty_lifted_by_other_state":"103089.769","month":"6","year":"122"},{"state_code":"21","statename":"ORISSA","total_txn_sold_to_other_state":"17","total_txn_lifted_by_other_state":"519","total_qty_sold_to_other_state":"549","total_qty_lifted_by_other_state":"15170.399","month":"6","year":"122"},{"state_code":"22","statename":"CHHATISGARH","total_txn_sold_to_other_state":"116","total_txn_lifted_by_other_state":"435","total_qty_sold_to_other_state":"3138.0","total_qty_lifted_by_other_state":"14119.819","month":"6","year":"122"},{"state_code":"23","statename":"MADHYA PRADESH","total_txn_sold_to_other_state":"671","total_txn_lifted_by_other_state":"9356","total_qty_sold_to_other_state":"23174.843","total_qty_lifted_by_other_state":"410586.157","month":"6","year":"122"},{"state_code":"24","statename":"GUJARAT","total_txn_sold_to_other_state":"2834","total_txn_lifted_by_other_state":"575","total_qty_sold_to_other_state":"122347.76","total_qty_lifted_by_other_state":"29859.729","month":"6","year":"122"},{"state_code":"25","statename":"DAMAN & DIU","total_txn_sold_to_other_state":"2571","total_txn_lifted_by_other_state":"6","total_qty_sold_to_other_state":"114450.144","total_qty_lifted_by_other_state":"225","month":"6","year":"122"},{"state_code":"27","statename":"MAHARASHTRA","total_txn_sold_to_other_state":"3623","total_txn_lifted_by_other_state":"1210","total_qty_sold_to_other_state":"147381.25","total_qty_lifted_by_other_state":"48449.243","month":"6","year":"122"},{"state_code":"28","statename":"ANDHRA PRADESH","total_txn_sold_to_other_state":"64","total_txn_lifted_by_other_state":"93","total_qty_sold_to_other_state":"905.5","total_qty_lifted_by_other_state":"1907","month":"6","year":"122"},{"state_code":"29","statename":"KARNATAKA","total_txn_sold_to_other_state":"731","total_txn_lifted_by_other_state":"719","total_qty_sold_to_other_state":"27076","total_qty_lifted_by_other_state":"20751.00","month":"6","year":"122"},{"state_code":"30","statename":"GOA","total_txn_sold_to_other_state":"388","total_txn_lifted_by_other_state":"3","total_qty_sold_to_other_state":"9514","total_qty_lifted_by_other_state":"108","month":"6","year":"122"},{"state_code":"32","statename":"KERALA","total_txn_sold_to_other_state":"925","total_txn_lifted_by_other_state":"59","total_qty_sold_to_other_state":"25667.9","total_qty_lifted_by_other_state":"947.885","month":"6","year":"122"},{"state_code":"33","statename":"TAMIL NADU","total_txn_sold_to_other_state":"217","total_txn_lifted_by_other_state":"359","total_qty_sold_to_other_state":"3066.90","total_qty_lifted_by_other_state":"3699.216","month":"6","year":"122"},{"state_code":"35","statename":"ANDAMAN & NICOBAR ISLANDS","total_txn_sold_to_other_state":"22","total_txn_lifted_by_other_state":"0","total_qty_sold_to_other_state":"242","total_qty_lifted_by_other_state":"0","month":"6","year":"122"},{"state_code":"36","statename":"TELANGANA","total_txn_sold_to_other_state":"170","total_txn_lifted_by_other_state":"74","total_qty_sold_to_other_state":"3361","total_qty_lifted_by_other_state":"1183","month":"6","year":"122"},{"state_code":"37","statename":"LADAKH","total_txn_sold_to_other_state":"28","total_txn_lifted_by_other_state":"0","total_qty_sold_to_other_state":"527.5","total_qty_lifted_by_other_state":"0","month":"6","year":"122"}]
