[{"state_code":"01","statename":"JAMMU AND KASHMIR","total_txn_sold_to_other_state":"188","total_txn_lifted_by_other_state":"196","total_qty_sold_to_other_state":"4744.0","total_qty_lifted_by_other_state":"3355.500","month":"2","year":"123"},{"state_code":"02","statename":"HIMACHAL PRADESH","total_txn_sold_to_other_state":"1634","total_txn_lifted_by_other_state":"39","total_qty_sold_to_other_state":"35538.0","total_qty_lifted_by_other_state":"801.0","month":"2","year":"123"},{"state_code":"05","statename":"UTTARAKHAND","total_txn_sold_to_other_state":"855","total_txn_lifted_by_other_state":"1928","total_qty_sold_to_other_state":"21442","total_qty_lifted_by_other_state":"49850.1","month":"2","year":"123"},{"state_code":"06","statename":"HARYANA","total_txn_sold_to_other_state":"2806","total_txn_lifted_by_other_state":"0","total_qty_sold_to_other_state":"67835.6","total_qty_lifted_by_other_state":"0","month":"2","year":"123"},{"state_code":"07","statename":"DELHI","total_txn_sold_to_other_state":"97795","total_txn_lifted_by_other_state":"0","total_qty_sold_to_other_state":"2115604.7","total_qty_lifted_by_other_state":"0","month":"2","year":"123"},{"state_code":"08","statename":"RAJASTHAN","total_txn_sold_to_other_state":"2880","total_txn_lifted_by_other_state":"589","total_qty_sold_to_other_state":"70906.51","total_qty_lifted_by_other_state":"12312.6","month":"2","year":"123"},{"state_code":"09","statename":"UTTAR PRADESH","total_txn_sold_to_other_state":"0","total_txn_lifted_by_other_state":"9194","total_qty_sold_to_other_state":"0","total_qty_lifted_by_other_state":"174705.00","month":"2","year":"123"},{"state_code":"10","statename":"BIHAR","total_txn_sold_to_other_state":"50","total_txn_lifted_by_other_state":"86125","total_qty_sold_to_other_state":"236.942","total_qty_lifted_by_other_state":"1887678.32","month":"2","year":"123"},{"state_code":"16","statename":"TRIPURA","total_txn_sold_to_other_state":"0","total_txn_lifted_by_other_state":"2","total_qty_sold_to_other_state":"0","total_qty_lifted_by_other_state":"47","month":"2","year":"123"},{"state_code":"18","statename":"ASSAM","total_txn_sold_to_other_state":"0","total_txn_lifted_by_other_state":"65","total_qty_sold_to_other_state":"0","total_qty_lifted_by_other_state":"1126.5","month":"2","year":"123"},{"state_code":"19","statename":"WEST BENGAL","total_txn_sold_to_other_state":"283","total_txn_lifted_by_other_state":"553","total_qty_sold_to_other_state":"3120.500","total_qty_lifted_by_other_state":"10912.01","month":"2","year":"123"},{"state_code":"20","statename":"JHARKHAND","total_txn_sold_to_other_state":"83","total_txn_lifted_by_other_state":"1682","total_qty_sold_to_other_state":"1925","total_qty_lifted_by_other_state":"36441.542","month":"2","year":"123"},{"state_code":"21","statename":"ORISSA","total_txn_sold_to_other_state":"6","total_txn_lifted_by_other_state":"22","total_qty_sold_to_other_state":"128","total_qty_lifted_by_other_state":"110","month":"2","year":"123"},{"state_code":"22","statename":"CHHATISGARH","total_txn_sold_to_other_state":"0","total_txn_lifted_by_other_state":"307","total_qty_sold_to_other_state":"0","total_qty_lifted_by_other_state":"6574.8","month":"2","year":"123"},{"state_code":"23","statename":"MADHYA PRADESH","total_txn_sold_to_other_state":"0","total_txn_lifted_by_other_state":"8422","total_qty_sold_to_other_state":"0","total_qty_lifted_by_other_state":"194914.9","month":"2","year":"123"},{"state_code":"24","statename":"GUJARAT","total_txn_sold_to_other_state":"766","total_txn_lifted_by_other_state":"109","total_qty_sold_to_other_state":"18755","total_qty_lifted_by_other_state":"3162.0","month":"2","year":"123"},{"state_code":"25","statename":"DAMAN & DIU","total_txn_sold_to_other_state":"316","total_txn_lifted_by_other_state":"2","total_qty_sold_to_other_state":"7324.0","total_qty_lifted_by_other_state":"50","month":"2","year":"123"},{"state_code":"27","statename":"MAHARASHTRA","total_txn_sold_to_other_state":"1283","total_txn_lifted_by_other_state":"398","total_qty_sold_to_other_state":"26775.975","total_qty_lifted_by_other_state":"9569.0","month":"2","year":"123"},{"state_code":"28","statename":"ANDHRA PRADESH","total_txn_sold_to_other_state":"7","total_txn_lifted_by_other_state":"304","total_qty_sold_to_other_state":"150","total_qty_lifted_by_other_state":"5920","month":"2","year":"123"},{"state_code":"29","statename":"KARNATAKA","total_txn_sold_to_other_state":"176","total_txn_lifted_by_other_state":"383","total_qty_sold_to_other_state":"3359","total_qty_lifted_by_other_state":"6776.50","month":"2","year":"123"},{"state_code":"30","statename":"GOA","total_txn_sold_to_other_state":"0","total_txn_lifted_by_other_state":"1","total_qty_sold_to_other_state":"0","total_qty_lifted_by_other_state":"30","month":"2","year":"123"},{"state_code":"32","statename":"KERALA","total_txn_sold_to_other_state":"547","total_txn_lifted_by_other_state":"18","total_qty_sold_to_other_state":"8817","total_qty_lifted_by_other_state":"336","month":"2","year":"123"},{"state_code":"33","statename":"TAMIL NADU","total_txn_sold_to_other_state":"163","total_txn_lifted_by_other_state":"518","total_qty_sold_to_other_state":"1917.92","total_qty_lifted_by_other_state":"2784.375","month":"2","year":"123"},{"state_code":"34","statename":"PUDUCHERRY","total_txn_sold_to_other_state":"194","total_txn_lifted_by_other_state":"0","total_qty_sold_to_other_state":"970","total_qty_lifted_by_other_state":"0","month":"2","year":"123"},{"state_code":"35","statename":"ANDAMAN & NICOBAR ISLANDS","total_txn_sold_to_other_state":"3","total_txn_lifted_by_other_state":"0","total_qty_sold_to_other_state":"35","total_qty_lifted_by_other_state":"0","month":"2","year":"123"},{"state_code":"36","statename":"TELANGANA","total_txn_sold_to_other_state":"822","total_txn_lifted_by_other_state":"0","total_qty_sold_to_other_state":"17872","total_qty_lifted_by_other_state":"0","month":"2","year":"123"}]
