[{"state_code":"01","statename":"JAMMU AND KASHMIR","total_txn_sold_to_other_state":"767","total_txn_lifted_by_other_state":"81","total_qty_sold_to_other_state":"16471.0","total_qty_lifted_by_other_state":"1535.0","month":"4","year":"123"},{"state_code":"02","statename":"HIMACHAL PRADESH","total_txn_sold_to_other_state":"5076","total_txn_lifted_by_other_state":"51","total_qty_sold_to_other_state":"123879.2","total_qty_lifted_by_other_state":"1055.6","month":"4","year":"123"},{"state_code":"03","statename":"PUNJAB","total_txn_sold_to_other_state":"18","total_txn_lifted_by_other_state":"0","total_qty_sold_to_other_state":"385","total_qty_lifted_by_other_state":"0","month":"4","year":"123"},{"state_code":"04","statename":"CHANDIGARH","total_txn_sold_to_other_state":"13","total_txn_lifted_by_other_state":"0","total_qty_sold_to_other_state":"200","total_qty_lifted_by_other_state":"0","month":"4","year":"123"},{"state_code":"05","statename":"UTTARAKHAND","total_txn_sold_to_other_state":"4279","total_txn_lifted_by_other_state":"2533","total_qty_sold_to_other_state":"103289.0","total_qty_lifted_by_other_state":"30872.06","month":"4","year":"123"},{"state_code":"06","statename":"HARYANA","total_txn_sold_to_other_state":"29758","total_txn_lifted_by_other_state":"91","total_qty_sold_to_other_state":"723001.638","total_qty_lifted_by_other_state":"94","month":"4","year":"123"},{"state_code":"07","statename":"DELHI","total_txn_sold_to_other_state":"213836","total_txn_lifted_by_other_state":"1653","total_qty_sold_to_other_state":"4541952.80","total_qty_lifted_by_other_state":"22381.28","month":"4","year":"123"},{"state_code":"08","statename":"RAJASTHAN","total_txn_sold_to_other_state":"7887","total_txn_lifted_by_other_state":"2156","total_qty_sold_to_other_state":"200225.01","total_qty_lifted_by_other_state":"45886.2","month":"4","year":"123"},{"state_code":"09","statename":"UTTAR PRADESH","total_txn_sold_to_other_state":"0","total_txn_lifted_by_other_state":"115732","total_qty_sold_to_other_state":"0","total_qty_lifted_by_other_state":"2375212.00","month":"4","year":"123"},{"state_code":"10","statename":"BIHAR","total_txn_sold_to_other_state":"2897","total_txn_lifted_by_other_state":"148146","total_qty_sold_to_other_state":"35276.88","total_qty_lifted_by_other_state":"3397825.002","month":"4","year":"123"},{"state_code":"11","statename":"SIKKIM","total_txn_sold_to_other_state":"39","total_txn_lifted_by_other_state":"0","total_qty_sold_to_other_state":"795","total_qty_lifted_by_other_state":"0","month":"4","year":"123"},{"state_code":"16","statename":"TRIPURA","total_txn_sold_to_other_state":"0","total_txn_lifted_by_other_state":"8","total_qty_sold_to_other_state":"0","total_qty_lifted_by_other_state":"154.5","month":"4","year":"123"},{"state_code":"17","statename":"MEGHALAYA","total_txn_sold_to_other_state":"4","total_txn_lifted_by_other_state":"0","total_qty_sold_to_other_state":"90","total_qty_lifted_by_other_state":"0","month":"4","year":"123"},{"state_code":"18","statename":"ASSAM","total_txn_sold_to_other_state":"0","total_txn_lifted_by_other_state":"159","total_qty_sold_to_other_state":"0","total_qty_lifted_by_other_state":"2402.0","month":"4","year":"123"},{"state_code":"19","statename":"WEST BENGAL","total_txn_sold_to_other_state":"608","total_txn_lifted_by_other_state":"1190","total_qty_sold_to_other_state":"13087.7","total_qty_lifted_by_other_state":"22820.01","month":"4","year":"123"},{"state_code":"20","statename":"JHARKHAND","total_txn_sold_to_other_state":"659","total_txn_lifted_by_other_state":"3784","total_qty_sold_to_other_state":"14985.75","total_qty_lifted_by_other_state":"77272.71","month":"4","year":"123"},{"state_code":"21","statename":"ORISSA","total_txn_sold_to_other_state":"1","total_txn_lifted_by_other_state":"70","total_qty_sold_to_other_state":"9","total_qty_lifted_by_other_state":"1091","month":"4","year":"123"},{"state_code":"22","statename":"CHHATISGARH","total_txn_sold_to_other_state":"38","total_txn_lifted_by_other_state":"725","total_qty_sold_to_other_state":"641","total_qty_lifted_by_other_state":"13292.20","month":"4","year":"123"},{"state_code":"23","statename":"MADHYA PRADESH","total_txn_sold_to_other_state":"1389","total_txn_lifted_by_other_state":"13766","total_qty_sold_to_other_state":"17323.8","total_qty_lifted_by_other_state":"320792.2","month":"4","year":"123"},{"state_code":"24","statename":"GUJARAT","total_txn_sold_to_other_state":"4524","total_txn_lifted_by_other_state":"398","total_qty_sold_to_other_state":"103193.85","total_qty_lifted_by_other_state":"10485.6","month":"4","year":"123"},{"state_code":"25","statename":"DAMAN & DIU","total_txn_sold_to_other_state":"2605","total_txn_lifted_by_other_state":"5","total_qty_sold_to_other_state":"62419.52","total_qty_lifted_by_other_state":"120","month":"4","year":"123"},{"state_code":"27","statename":"MAHARASHTRA","total_txn_sold_to_other_state":"17283","total_txn_lifted_by_other_state":"1375","total_qty_sold_to_other_state":"367718.372","total_qty_lifted_by_other_state":"27303.47","month":"4","year":"123"},{"state_code":"28","statename":"ANDHRA PRADESH","total_txn_sold_to_other_state":"0","total_txn_lifted_by_other_state":"565","total_qty_sold_to_other_state":"0","total_qty_lifted_by_other_state":"10640","month":"4","year":"123"},{"state_code":"29","statename":"KARNATAKA","total_txn_sold_to_other_state":"385","total_txn_lifted_by_other_state":"795","total_qty_sold_to_other_state":"7747","total_qty_lifted_by_other_state":"14876.60","month":"4","year":"123"},{"state_code":"30","statename":"GOA","total_txn_sold_to_other_state":"548","total_txn_lifted_by_other_state":"6","total_qty_sold_to_other_state":"11784.5","total_qty_lifted_by_other_state":"85","month":"4","year":"123"},{"state_code":"32","statename":"KERALA","total_txn_sold_to_other_state":"736","total_txn_lifted_by_other_state":"66","total_qty_sold_to_other_state":"11084","total_qty_lifted_by_other_state":"911.5","month":"4","year":"123"},{"state_code":"33","statename":"TAMIL NADU","total_txn_sold_to_other_state":"359","total_txn_lifted_by_other_state":"1945","total_qty_sold_to_other_state":"3655.12","total_qty_lifted_by_other_state":"11798.208","month":"4","year":"123"},{"state_code":"34","statename":"PUDUCHERRY","total_txn_sold_to_other_state":"194","total_txn_lifted_by_other_state":"0","total_qty_sold_to_other_state":"970","total_qty_lifted_by_other_state":"0","month":"4","year":"123"},{"state_code":"35","statename":"ANDAMAN & NICOBAR ISLANDS","total_txn_sold_to_other_state":"9","total_txn_lifted_by_other_state":"0","total_qty_sold_to_other_state":"145.0","total_qty_lifted_by_other_state":"0","month":"4","year":"123"},{"state_code":"36","statename":"TELANGANA","total_txn_sold_to_other_state":"1385","total_txn_lifted_by_other_state":"0","total_qty_sold_to_other_state":"28564","total_qty_lifted_by_other_state":"0","month":"4","year":"123"},{"state_code":"37","statename":"LADAKH","total_txn_sold_to_other_state":"3","total_txn_lifted_by_other_state":"0","total_qty_sold_to_other_state":"12","total_qty_lifted_by_other_state":"0","month":"4","year":"123"}]
