[{"state_code":"02","statename":"HIMACHAL PRADESH","total_txn_sold_to_other_state":"93","total_txn_lifted_by_other_state":"10","total_qty_sold_to_other_state":"4290.008","total_qty_lifted_by_other_state":"354","month":"10","year":"121"},{"state_code":"03","statename":"PUNJAB","total_txn_sold_to_other_state":"314","total_txn_lifted_by_other_state":"0","total_qty_sold_to_other_state":"10915","total_qty_lifted_by_other_state":"0","month":"10","year":"121"},{"state_code":"05","statename":"UTTARAKHAND","total_txn_sold_to_other_state":"718","total_txn_lifted_by_other_state":"78","total_qty_sold_to_other_state":"19105","total_qty_lifted_by_other_state":"1971.00","month":"10","year":"121"},{"state_code":"06","statename":"HARYANA","total_txn_sold_to_other_state":"252","total_txn_lifted_by_other_state":"364","total_qty_sold_to_other_state":"7285","total_qty_lifted_by_other_state":"8784.008","month":"10","year":"121"},{"state_code":"07","statename":"DELHI","total_txn_sold_to_other_state":"15935","total_txn_lifted_by_other_state":"0","total_qty_sold_to_other_state":"738848.861","total_qty_lifted_by_other_state":"0","month":"10","year":"121"},{"state_code":"08","statename":"RAJASTHAN","total_txn_sold_to_other_state":"25","total_txn_lifted_by_other_state":"268","total_qty_sold_to_other_state":"965","total_qty_lifted_by_other_state":"11287.00","month":"10","year":"121"},{"state_code":"09","statename":"UTTAR PRADESH","total_txn_sold_to_other_state":"0","total_txn_lifted_by_other_state":"6368","total_qty_sold_to_other_state":"0","total_qty_lifted_by_other_state":"268505.00","month":"10","year":"121"},{"state_code":"10","statename":"BIHAR","total_txn_sold_to_other_state":"65","total_txn_lifted_by_other_state":"10088","total_qty_sold_to_other_state":"2392","total_qty_lifted_by_other_state":"472280.982","month":"10","year":"121"},{"state_code":"16","statename":"TRIPURA","total_txn_sold_to_other_state":"2","total_txn_lifted_by_other_state":"3","total_qty_sold_to_other_state":"70","total_qty_lifted_by_other_state":"50","month":"10","year":"121"},{"state_code":"19","statename":"WEST BENGAL","total_txn_sold_to_other_state":"4","total_txn_lifted_by_other_state":"119","total_qty_sold_to_other_state":"132","total_qty_lifted_by_other_state":"3320","month":"10","year":"121"},{"state_code":"20","statename":"JHARKHAND","total_txn_sold_to_other_state":"17","total_txn_lifted_by_other_state":"235","total_qty_sold_to_other_state":"760","total_qty_lifted_by_other_state":"8639.999","month":"10","year":"121"},{"state_code":"21","statename":"ORISSA","total_txn_sold_to_other_state":"8","total_txn_lifted_by_other_state":"70","total_qty_sold_to_other_state":"270","total_qty_lifted_by_other_state":"2040.00","month":"10","year":"121"},{"state_code":"23","statename":"MADHYA PRADESH","total_txn_sold_to_other_state":"10","total_txn_lifted_by_other_state":"434","total_qty_sold_to_other_state":"536","total_qty_lifted_by_other_state":"19682.00","month":"10","year":"121"},{"state_code":"24","statename":"GUJARAT","total_txn_sold_to_other_state":"0","total_txn_lifted_by_other_state":"31","total_qty_sold_to_other_state":"0","total_qty_lifted_by_other_state":"1497.1","month":"10","year":"121"},{"state_code":"25","statename":"DAMAN & DIU","total_txn_sold_to_other_state":"12","total_txn_lifted_by_other_state":"0","total_qty_sold_to_other_state":"424.6","total_qty_lifted_by_other_state":"0","month":"10","year":"121"},{"state_code":"27","statename":"MAHARASHTRA","total_txn_sold_to_other_state":"118","total_txn_lifted_by_other_state":"0","total_qty_sold_to_other_state":"4454.5","total_qty_lifted_by_other_state":"0","month":"10","year":"121"},{"state_code":"28","statename":"ANDHRA PRADESH","total_txn_sold_to_other_state":"0","total_txn_lifted_by_other_state":"92","total_qty_sold_to_other_state":"0","total_qty_lifted_by_other_state":"1964","month":"10","year":"121"},{"state_code":"29","statename":"KARNATAKA","total_txn_sold_to_other_state":"18","total_txn_lifted_by_other_state":"0","total_qty_sold_to_other_state":"474","total_qty_lifted_by_other_state":"0","month":"10","year":"121"},{"state_code":"30","statename":"GOA","total_txn_sold_to_other_state":"21","total_txn_lifted_by_other_state":"0","total_qty_sold_to_other_state":"690","total_qty_lifted_by_other_state":"0","month":"10","year":"121"},{"state_code":"32","statename":"KERALA","total_txn_sold_to_other_state":"54","total_txn_lifted_by_other_state":"5","total_qty_sold_to_other_state":"1085","total_qty_lifted_by_other_state":"101","month":"10","year":"121"},{"state_code":"33","statename":"TAMIL NADU","total_txn_sold_to_other_state":"429","total_txn_lifted_by_other_state":"21","total_qty_sold_to_other_state":"6083.12","total_qty_lifted_by_other_state":"213","month":"10","year":"121"},{"state_code":"36","statename":"TELANGANA","total_txn_sold_to_other_state":"95","total_txn_lifted_by_other_state":"4","total_qty_sold_to_other_state":"1999","total_qty_lifted_by_other_state":"90","month":"10","year":"121"}]
