[{"state_code":"01","statename":"JAMMU AND KASHMIR","total_txn_sold_to_other_state":"570","total_txn_lifted_by_other_state":"21","total_qty_sold_to_other_state":"5038.8","total_qty_lifted_by_other_state":"885","month":"9","year":"122"},{"state_code":"02","statename":"HIMACHAL PRADESH","total_txn_sold_to_other_state":"955","total_txn_lifted_by_other_state":"39","total_qty_sold_to_other_state":"29898.375","total_qty_lifted_by_other_state":"1520.0","month":"9","year":"122"},{"state_code":"05","statename":"UTTARAKHAND","total_txn_sold_to_other_state":"806","total_txn_lifted_by_other_state":"1562","total_qty_sold_to_other_state":"20231","total_qty_lifted_by_other_state":"42008.78","month":"9","year":"122"},{"state_code":"06","statename":"HARYANA","total_txn_sold_to_other_state":"2841","total_txn_lifted_by_other_state":"1596","total_qty_sold_to_other_state":"117874","total_qty_lifted_by_other_state":"68989.6","month":"9","year":"122"},{"state_code":"07","statename":"DELHI","total_txn_sold_to_other_state":"103665","total_txn_lifted_by_other_state":"0","total_qty_sold_to_other_state":"4209084.20","total_qty_lifted_by_other_state":"0","month":"9","year":"122"},{"state_code":"08","statename":"RAJASTHAN","total_txn_sold_to_other_state":"1527","total_txn_lifted_by_other_state":"1272","total_qty_sold_to_other_state":"63090.625","total_qty_lifted_by_other_state":"54139.8","month":"9","year":"122"},{"state_code":"09","statename":"UTTAR PRADESH","total_txn_sold_to_other_state":"0","total_txn_lifted_by_other_state":"25898","total_qty_sold_to_other_state":"0","total_qty_lifted_by_other_state":"564102.00","month":"9","year":"122"},{"state_code":"10","statename":"BIHAR","total_txn_sold_to_other_state":"492","total_txn_lifted_by_other_state":"73093","total_qty_sold_to_other_state":"16234","total_qty_lifted_by_other_state":"3362680.585","month":"9","year":"122"},{"state_code":"11","statename":"SIKKIM","total_txn_sold_to_other_state":"3","total_txn_lifted_by_other_state":"0","total_qty_sold_to_other_state":"90","total_qty_lifted_by_other_state":"0","month":"9","year":"122"},{"state_code":"16","statename":"TRIPURA","total_txn_sold_to_other_state":"18","total_txn_lifted_by_other_state":"0","total_qty_sold_to_other_state":"625","total_qty_lifted_by_other_state":"0","month":"9","year":"122"},{"state_code":"18","statename":"ASSAM","total_txn_sold_to_other_state":"0","total_txn_lifted_by_other_state":"44","total_qty_sold_to_other_state":"0","total_qty_lifted_by_other_state":"1356","month":"9","year":"122"},{"state_code":"19","statename":"WEST BENGAL","total_txn_sold_to_other_state":"47","total_txn_lifted_by_other_state":"685","total_qty_sold_to_other_state":"1716.3","total_qty_lifted_by_other_state":"26856.025","month":"9","year":"122"},{"state_code":"20","statename":"JHARKHAND","total_txn_sold_to_other_state":"57","total_txn_lifted_by_other_state":"833","total_qty_sold_to_other_state":"2385","total_qty_lifted_by_other_state":"38282.1","month":"9","year":"122"},{"state_code":"21","statename":"ORISSA","total_txn_sold_to_other_state":"6","total_txn_lifted_by_other_state":"237","total_qty_sold_to_other_state":"237","total_qty_lifted_by_other_state":"6813.4","month":"9","year":"122"},{"state_code":"22","statename":"CHHATISGARH","total_txn_sold_to_other_state":"51","total_txn_lifted_by_other_state":"223","total_qty_sold_to_other_state":"1299","total_qty_lifted_by_other_state":"7692.2","month":"9","year":"122"},{"state_code":"23","statename":"MADHYA PRADESH","total_txn_sold_to_other_state":"334","total_txn_lifted_by_other_state":"7846","total_qty_sold_to_other_state":"9039.2","total_qty_lifted_by_other_state":"356383.8","month":"9","year":"122"},{"state_code":"24","statename":"GUJARAT","total_txn_sold_to_other_state":"111","total_txn_lifted_by_other_state":"120","total_qty_sold_to_other_state":"2478","total_qty_lifted_by_other_state":"5497.5","month":"9","year":"122"},{"state_code":"25","statename":"DAMAN & DIU","total_txn_sold_to_other_state":"315","total_txn_lifted_by_other_state":"3","total_qty_sold_to_other_state":"11792.7","total_qty_lifted_by_other_state":"76.0","month":"9","year":"122"},{"state_code":"27","statename":"MAHARASHTRA","total_txn_sold_to_other_state":"1132","total_txn_lifted_by_other_state":"49","total_qty_sold_to_other_state":"34424.00","total_qty_lifted_by_other_state":"1542.0","month":"9","year":"122"},{"state_code":"28","statename":"ANDHRA PRADESH","total_txn_sold_to_other_state":"33","total_txn_lifted_by_other_state":"136","total_qty_sold_to_other_state":"714","total_qty_lifted_by_other_state":"2897","month":"9","year":"122"},{"state_code":"29","statename":"KARNATAKA","total_txn_sold_to_other_state":"61","total_txn_lifted_by_other_state":"277","total_qty_sold_to_other_state":"1871","total_qty_lifted_by_other_state":"8028.00","month":"9","year":"122"},{"state_code":"30","statename":"GOA","total_txn_sold_to_other_state":"169","total_txn_lifted_by_other_state":"0","total_qty_sold_to_other_state":"3937","total_qty_lifted_by_other_state":"0","month":"9","year":"122"},{"state_code":"32","statename":"KERALA","total_txn_sold_to_other_state":"409","total_txn_lifted_by_other_state":"13","total_qty_sold_to_other_state":"11504","total_qty_lifted_by_other_state":"420","month":"9","year":"122"},{"state_code":"33","statename":"TAMIL NADU","total_txn_sold_to_other_state":"257","total_txn_lifted_by_other_state":"125","total_qty_sold_to_other_state":"3156.59","total_qty_lifted_by_other_state":"1101.0","month":"9","year":"122"},{"state_code":"35","statename":"ANDAMAN & NICOBAR ISLANDS","total_txn_sold_to_other_state":"3","total_txn_lifted_by_other_state":"0","total_qty_sold_to_other_state":"74","total_qty_lifted_by_other_state":"0","month":"9","year":"122"},{"state_code":"36","statename":"TELANGANA","total_txn_sold_to_other_state":"220","total_txn_lifted_by_other_state":"10","total_qty_sold_to_other_state":"4682","total_qty_lifted_by_other_state":"205","month":"9","year":"122"}]
